<?xml version="1.0"?>
<swistrackcomponent>
	<friendlyname>Morphology</friendlyname>
	<description>Multi-purpose morpholohy component, where operation:
	</description>
	<url>http://en.wikibooks.org/wiki/SwisTrack/Components/Morphology</url>
	<displayimage>Output</displayimage>

	<configuration>
		<line />
		<title>Parameters</title>
		<parameter type="dropdownlist">
	    		<name>Operation</name>
	    		<label>Operations</label>
	    		<items>
	    		  <item key="0">OPEN</item>
	    		  <item key="1">CLOSE</item>
	    		  <item key="2">GRADIENT</item>
			  <item key="3">TOPHAT</item>
			  <item key="4">BLACKHAT</item>
			</items>
	    		<default>1</default>
	    		<reloadable>true</reloadable>
	  	</parameter>
		<parameter type="integer">
			<name>Iterations</name>
			<label>Number of iterations</label>
			<min>1</min>
			<default>1</default>
			<max>5</max>
			<unit>iterations</unit>
			<slider>true</slider>
			<sliderstep>1</sliderstep>
			<reloadable>true</reloadable>
		</parameter>
	</configuration>
</swistrackcomponent>
